pairing_functions/__init__.py
pairing_functions/__version__.py
pairing_functions/cantor.py
pairing_functions/szudzik.py
pairing_functions-0.2.1.dist-info/AUTHORS.rst
pairing_functions-0.2.1.dist-info/LICENSE
pairing_functions-0.2.1.dist-info/METADATA
pairing_functions-0.2.1.dist-info/WHEEL
pairing_functions-0.2.1.dist-info/top_level.txt
pairing_functions-0.2.1.dist-info/RECORD
