Metadata-Version: 2.1
Name: pairing-functions
Version: 0.2.1
Summary: A collection of pairing functions
Home-page: https://github.com/ConvertGroupLabs/pairing-functions
Author: Convert Group Labs
Author-email: tools@convertgroup.com
License: MIT License
Platform: UNKNOWN
Classifier: Natural Language :: English
Classifier: License :: OSI Approved :: MIT License
Classifier: Programming Language :: Python
Classifier: Programming Language :: Python :: 3
Classifier: Programming Language :: Python :: 3.6
Classifier: Programming Language :: Python :: Implementation :: CPython
Classifier: Programming Language :: Python :: Implementation :: PyPy
Requires-Python: >=3.5.2
